geoint/__init__.py
geoint/geospatial.py
geoint-0.2.dist-info/LICENSE
geoint-0.2.dist-info/METADATA
geoint-0.2.dist-info/WHEEL
geoint-0.2.dist-info/top_level.txt
geoint-0.2.dist-info/RECORD
