Metadata-Version: 2.1
Name: geoint
Version: 0.2
Summary: Simple python module for geospatial intelligence workflows.
Home-page: https://github.com/gisfromscratch/geoint-py
Author: Jan Tschada
Author-email: gisfromscratch@live.de
License: UNKNOWN
Platform: UNKNOWN
Classifier: Programming Language :: Python :: 3
Classifier: License :: OSI Approved :: GNU Lesser General Public License v3 (LGPLv3)
Classifier: Operating System :: OS Independent
License-File: LICENSE
Requires-Dist: arcgis (>=1.8)
Requires-Dist: georapid (>=0.2)
Requires-Dist: pandas (>=1.5)
